hpcworkshop/__init__.py
hpcworkshop/main.py
hpcworkshop/cmd/__init__.py
hpcworkshop/cmd/build-container.py
hpcworkshop/cmd/build_container.py
hpcworkshop/cmd/destroy.py
hpcworkshop/cmd/init.py
hpcworkshop/cmd/setup-module.py
hpcworkshop/cmd/setup_ldap.py
hpcworkshop/cmd/setup_module.py
hpcworkshop/cmd/setup_nfs.py
hpcworkshop/cmd/setup_slurm.py
hpcworkshop/cmd/spack_install.py
hpc_workshop-1.1.1.dist-info/LICENSE
hpc_workshop-1.1.1.dist-info/METADATA
hpc_workshop-1.1.1.dist-info/WHEEL
hpc_workshop-1.1.1.dist-info/entry_points.txt
hpc_workshop-1.1.1.dist-info/top_level.txt
hpc_workshop-1.1.1.dist-info/RECORD
